redminebotlib/__init__.py
redminebotlib/async_tests.py
redminebotlib/constants.py
redminebotlib/core.py
redminebotlib/data_structs.py
redminebotlib/default_scenery_api_realisation.py
redminebotlib/http_req_lib.py
redminebotlib/server_control_unit.py
redminebotlib-2023.9b4.dist-info/LICENSE
redminebotlib-2023.9b4.dist-info/METADATA
redminebotlib-2023.9b4.dist-info/WHEEL
redminebotlib-2023.9b4.dist-info/top_level.txt
redminebotlib-2023.9b4.dist-info/RECORD
