Metadata-Version: 2.1
Name: redminebotlib
Version: 2023.9b4
Summary: Library for creating chat-bot to control Redmine
Home-page: https://github.com/Fe-Ti/Redmine-Bot-Library
Author: Fe-Ti
Author-email: btm.007@mail.ru
Project-URL: Bug Tracker, https://github.com/Fe-Ti/Redmine-Bot-Library/issues
Classifier: Programming Language :: Python :: 3
Classifier: License :: OSI Approved :: BSD License
Classifier: Operating System :: Unix
Requires-Python: >=3.10
License-File: LICENSE
